CHANGELOG.md
LICENSE
MANIFEST.in
README.md
setup.cfg
setup.py
test/test_extent.py
usgs_topo_tiler/__init__.py
usgs_topo_tiler/cli.py
usgs_topo_tiler/cutline.py
usgs_topo_tiler/extent.py
usgs_topo_tiler/usgs_topo.py
usgs_topo_tiler.egg-info/PKG-INFO
usgs_topo_tiler.egg-info/SOURCES.txt
usgs_topo_tiler.egg-info/dependency_links.txt
usgs_topo_tiler.egg-info/entry_points.txt
usgs_topo_tiler.egg-info/not-zip-safe
usgs_topo_tiler.egg-info/requires.txt
usgs_topo_tiler.egg-info/top_level.txt
usgs_topo_tiler/scripts/__init__.py
usgs_topo_tiler/scripts/list_s3.py
usgs_topo_tiler/scripts/metadata.py
usgs_topo_tiler/scripts/mosaic.py
usgs_topo_tiler/scripts/mosaic_bulk.py